rainiee_lib/__init__.py
rainiee_lib/client/__init__.py
rainiee_lib/client/boto_client.py
rainiee_lib/client/client_factory.py
rainiee_lib/client/feishu_client.py
rainiee_lib/constants/__init__.py
rainiee_lib/constants/data_consts.py
rainiee_lib/constants/param_consts.py
rainiee_lib/dataframe/__init__.py
rainiee_lib/dataframe/pandas_df.py
rainiee_lib/lib/__init__.py
rainiee_lib/lib/computation.py
rainiee_lib/lib/database_utils.py
rainiee_lib/lib/utils.py
rainiee_lib/objects/__init__.py
rainiee_lib/objects/objects_utils.py
rainiee_lib/objects/assets/__init__.py
rainiee_lib/objects/assets/asset.py
rainiee_lib/objects/backtesting/__init__.py
rainiee_lib/objects/backtesting/backtest_result.py
rainiee_lib/objects/backtesting/strategy_result.py
rainiee_lib/objects/base/__init__.py
rainiee_lib/objects/base/base_object.py
rainiee_lib/objects/funnels/__init__.py
rainiee_lib/objects/funnels/funnels.py
rainiee_lib/objects/orders/__init__.py
rainiee_lib/objects/orders/order.py
rainiee_lib/objects/portfolio/__init__.py
rainiee_lib/objects/portfolio/portfolio.py
rainiee_lib/objects/predictions/__init__.py
rainiee_lib/objects/predictions/ret_predictions.py
rainiee_lib/objects/stocks/__init__.py
rainiee_lib/objects/stocks/indexs.py
rainiee_lib/objects/stocks/stocks.py
rainiee_lib/plotting/__init__.py
rainiee_lib/plotting/plot.py
rainiee_lib-1.0.8.112405.dist-info/METADATA
rainiee_lib-1.0.8.112405.dist-info/WHEEL
rainiee_lib-1.0.8.112405.dist-info/top_level.txt
rainiee_lib-1.0.8.112405.dist-info/RECORD
